{"visible": {"type": 0, "list_id": 0}, "created_at": "Tue Mar 07 15:03:22 +0800 2017", "id": "4082679894291208", "mid": "4082679894291208", "can_edit": false, "show_additional_indication": 0, "text": "\u5584\u5fc3\u83b2\u5fc3\u6350\u52a9\u5fae\u516c\u76ca\u641c\u72d0\u7126\u70b9\u516c\u76ca\u57fa\u91d181147\u5143\uff0c\u4e3a6\u540d\u5148\u5fc3\u75c5\u60a3\u513f\u8865\u9f50\u4e86\u624b\u672f\u8d39\uff0c\u89e3\u71c3\u7709\u4e4b\u6025\uff0c\u53ef\u7acb\u5373\u65bd\u884c\u624b\u672f\u6cbb\u7597\u3002<br />-----\u201c\u4e0e\u5176\u505a\u4e00\u4e16\u7099\u624b\u53ef\u70ed\u7684\u70b9\u949e\u673a\u53ca\u9996\u9970\u7bb1\uff0c\u4e0d\u5982\u505a\u4e00\u4e2a\u6697\u6697\u5229\u4eba\u5176\u8c8c\u4e0d\u626c\u7684\u767e\u5b50\u67dc\u3002\u91d1\u94f6\u73e0\u5b9d\u5e03\u65bd\u5728\u82e6\u96be\u4eba\u8eab\u4e0a\uff0c\u4fbf\u6210\u5c31\u5b83\u6c38\u4e0d\u78e8\u706d\u7684\u4ef7\u503c\uff1b\u7531\u7480\u74a8\u593a\u76ee\u66f4\u5316\u4e3a\u7965\u5149\u4e07\u5ea6\uff0c\u4ee5\u6709\u9650\u53d8\u65e0\u9650\uff0c\u4ece\u751f\u706d ...<a href=\"/status/4082679894291208\">\u5168\u6587</a>", "textLength": 322, "source": "", "favorited": false, "pic_ids": ["8f5a40f3ly1fdeaen0zbvj212x0kytdu", "8f5a40f3ly1fdeaeorjc9j212z0m00yb", "8f5a40f3ly1fdeaeqa6efj212w0m3afo", "8f5a40f3ly1fdeaerwzouj21320mo79h", "8f5a40f3ly1fdeaeze55xj212w0npq9b", "8f5a40f3ly1fdeaey24zyj212k0nrkjl", "8f5a40f3ly1fdeaf2dd50j20pn0lvneg", "8f5a40f3ly1fdeaf59lh5j20ps0lrk8m"], "pic_types": "", "thumbnail_pic": "https://wx2.sinaimg.cn/thumbnail/8f5a40f3ly1fdeaen0zbvj212x0kytdu.jpg", "bmiddle_pic": "http://wx2.sinaimg.cn/bmiddle/8f5a40f3ly1fdeaen0zbvj212x0kytdu.jpg", "original_pic": "https://wx2.sinaimg.cn/large/8f5a40f3ly1fdeaen0zbvj212x0kytdu.jpg", "is_paid": false, "mblog_vip_type": 0, "user": {"id": 2405056755, "screen_name": "\u5584\u5fc3\u83b2\u5fc3\u5fae\u535a", "profile_image_url": "https://tva1.sinaimg.cn/crop.0.0.180.180.180/8f5a40f3jw1e8qgp5bmzyj2050050aa8.jpg?KID=imgbed,tva&Expires=1642955235&ssig=3l%2BrvPEi11", "profile_url": "https://m.weibo.cn/u/2405056755?uid=2405056755&luicode=10000011&lfid=1076032405056755", "statuses_count": 2539, "verified": false, "verified_type": -1, "close_blue_v": false, "description": "\u5584\u5fc3\u84ee\u5fc3\uff0c\u842c\u773e\u540c\u5fc3\u3002", "gender": "m", "mbtype": 12, "urank": 37, "mbrank": 7, "follow_me": false, "following": false, "follow_count": 12, "followers_count": "5300", "followers_count_str": "5300", "cover_image_phone": "https://tva1.sinaimg.cn/crop.0.0.640.640.640/549d0121tw1egm1kjly3jj20hs0hsq4f.jpg", "avatar_hd": "https://ww1.sinaimg.cn/orj480/8f5a40f3jw1e8qgp5bmzyj2050050aa8.jpg", "like": false, "like_me": false, "badge": {"bind_taobao": 1, "user_name_certificate": 1, "yiqijuan_2018": 1, "renrengongyijie_2021": 1}}, "picStatus": "0:1,1:1,2:1,3:1,4:1,5:1,6:1,7:1", "reposts_count": 3, "comments_count": 3, "reprint_cmt_count": 0, "attitudes_count": 21, "pending_approval_count": 0, "isLongText": true, "reward_exhibition_type": 0, "hide_flag": 0, "mlevel": 0, "darwin_tags": [], "mblogtype": 0, "rid": "5_0_50_5053202892646499965_0_0_0", "more_info_type": 0, "extern_safe": 0, "number_display_strategy": {"apply_scenario_flag": 3, "display_text_min_number": 1000000, "display_text": "100\u4e07+"}, "enable_comment_guide": true, "content_auth": 0, "pic_num": 8, "alchemy_params": {"ug_red_envelope": false}, "reprint_type": 0, "can_reprint": false, "new_comment_style": 0, "mblog_menu_new_style": 0, "edit_config": {"edited": false}, "pics": [{"pid": "8f5a40f3ly1fdeaen0zbvj212x0kytdu", "url": "https://wx2.sinaimg.cn/orj360/8f5a40f3ly1fdeaen0zbvj212x0kytdu.jpg", "size": "orj360", "geo": {"width": 501, "height": 270, "croped": false}, "large": {"size": "large", "url": "https://wx2.sinaimg.cn/large/8f5a40f3ly1fdeaen0zbvj212x0kytdu.jpg", "geo": {"width": "1401", "height": "754", "croped": false}}}, {"pid": "8f5a40f3ly1fdeaeorjc9j212z0m00yb", "url": "https://wx2.sinaimg.cn/orj360/8f5a40f3ly1fdeaeorjc9j212z0m00yb.jpg", "size": "orj360", "geo": {"width": 478, "height": 270, "croped": false}, "large": {"size": "large", "url": "https://wx2.sinaimg.cn/large/8f5a40f3ly1fdeaeorjc9j212z0m00yb.jpg", "geo": {"width": "1403", "height": "792", "croped": false}}}, {"pid": "8f5a40f3ly1fdeaeqa6efj212w0m3afo", "url": "https://wx1.sinaimg.cn/orj360/8f5a40f3ly1fdeaeqa6efj212w0m3afo.jpg", "size": "orj360", "geo": {"width": 475, "height": 270, "croped": false}, "large": {"size": "large", "url": "https://wx1.sinaimg.cn/large/8f5a40f3ly1fdeaeqa6efj212w0m3afo.jpg", "geo": {"width": "1400", "height": "795", "croped": false}}}, {"pid": "8f5a40f3ly1fdeaerwzouj21320mo79h", "url": "https://wx2.sinaimg.cn/orj360/8f5a40f3ly1fdeaerwzouj21320mo79h.jpg", "size": "orj360", "geo": {"width": 465, "height": 270, "croped": false}, "large": {"size": "large", "url": "https://wx2.sinaimg.cn/large/8f5a40f3ly1fdeaerwzouj21320mo79h.jpg", "geo": {"width": "1406", "height": "816", "croped": false}}}, {"pid": "8f5a40f3ly1fdeaeze55xj212w0npq9b", "url": "https://wx4.sinaimg.cn/orj360/8f5a40f3ly1fdeaeze55xj212w0npq9b.jpg", "size": "orj360", "geo": {"width": 443, "height": 270, "croped": false}, "large": {"size": "large", "url": "https://wx4.sinaimg.cn/large/8f5a40f3ly1fdeaeze55xj212w0npq9b.jpg", "geo": {"width": "1400", "height": "853", "croped": false}}}, {"pid": "8f5a40f3ly1fdeaey24zyj212k0nrkjl", "url": "https://wx2.sinaimg.cn/orj360/8f5a40f3ly1fdeaey24zyj212k0nrkjl.jpg", "size": "orj360", "geo": {"width": 438, "height": 270, "croped": false}, "large": {"size": "large", "url": "https://wx2.sinaimg.cn/large/8f5a40f3ly1fdeaey24zyj212k0nrkjl.jpg", "geo": {"width": "1388", "height": "855", "croped": false}}}, {"pid": "8f5a40f3ly1fdeaf2dd50j20pn0lvneg", "url": "https://wx4.sinaimg.cn/orj360/8f5a40f3ly1fdeaf2dd50j20pn0lvneg.jpg", "size": "orj360", "geo": {"width": 316, "height": 270, "croped": false}, "large": {"size": "large", "url": "https://wx4.sinaimg.cn/large/8f5a40f3ly1fdeaf2dd50j20pn0lvneg.jpg", "geo": {"width": "923", "height": "787", "croped": false}}}, {"pid": "8f5a40f3ly1fdeaf59lh5j20ps0lrk8m", "url": "https://wx1.sinaimg.cn/orj360/8f5a40f3ly1fdeaf59lh5j20ps0lrk8m.jpg", "size": "orj360", "geo": {"width": 320, "height": 270, "croped": false}, "large": {"size": "large", "url": "https://wx1.sinaimg.cn/large/8f5a40f3ly1fdeaf59lh5j20ps0lrk8m.jpg", "geo": {"width": "928", "height": "783", "croped": false}}}], "bid": "EyGSFi0l2"}