{"visible": {"type": 0, "list_id": 0}, "created_at": "Sat Apr 20 22:59:53 +0800 2019", "id": "4363288021847174", "mid": "4363288021847174", "can_edit": false, "show_additional_indication": 0, "text": "\u201c\u7a3d\u9996\u7688\u4f9d\u82cf\u6089\u5e1d\uff0c\u5934\u9762\u9876\u793c\u4e03\u4ff1\u80dd\uff1b\u6211\u4eca\u79f0\u8d5e\u5927\u51c6\u63d0\uff0c\u552f\u613f\u6148\u60b2\u5782\u52a0\u62a4\u3002\u201d\u4eca\u65e5\u662f\u51c6\u63d0\u83e9\u8428\u5723\u8bde\u7eaa\u5ff5\u65e5\uff0c\u5728\u8fd9\u5409\u7965\u7684\u65e5\u5b50\u91cc\uff0c\u5584\u5fc3\u83b2\u5fc3\u5404\u5730\u540c\u5b66\u66f4\u52a0\u8e0a\u8dc3\u653e\u751f\uff0c\u5171\u540c\u7948\u613f\u4e16\u754c\u548c\u5e73\uff0c\u5404\u79cd\u707e\u96be\u761f\u75ab\u6d88\u9664\uff0c\u4f17\u751f\u5b89\u4e50\uff01<span class=\"url-icon\"><img alt=[\u7ed9\u529b] src=\"https://h5.sinaimg.cn/m/emoticon/icon/others/f_geili-78be8d9152.png\" style=\"width:1em; height:1em;\" /></span><span class=\"url-icon\"><img alt=[\u5a01\u6b66] src=\"https://h5.sinaimg.cn/m/emoticon/icon/others/f_v5-bbd6f199c2.png\" style=\"width:1em; height:1em;\" /></span><span class=\"url-icon\"><img alt=[\u5fc3] src=\"https://h5.sinaimg.cn/m/emoticon/icon/others/l_xin-43af9086c0.png\" style=\"width:1em; height:1em;\" /></span> ", "textLength": 204, "source": "", "favorited": false, "pic_ids": ["8f5a40f3ly1g29hszodkej216o16o7wh", "8f5a40f3ly1g29ht0ti64j216o16o4ox", "8f5a40f3ly1g29ht2sf9hj216o16otyn", "8f5a40f3ly1g29ht5r84fj216o16o4qp", "8f5a40f3ly1g29ht7fyecj216o16oe6x", "8f5a40f3ly1g29ht8nqt4j216o16o7uk", "8f5a40f3ly1g29htb6tjsj216o16o4qp", "8f5a40f3ly1g29htdrxhjj216o16o1kx", "8f5a40f3ly1g29htghwxcj216o16okib"], "pic_types": "0,0,0,0,0,0,0,0,0", "thumbnail_pic": "https://wx3.sinaimg.cn/thumbnail/8f5a40f3ly1g29hszodkej216o16o7wh.jpg", "bmiddle_pic": "http://wx3.sinaimg.cn/bmiddle/8f5a40f3ly1g29hszodkej216o16o7wh.jpg", "original_pic": "https://wx3.sinaimg.cn/large/8f5a40f3ly1g29hszodkej216o16o7wh.jpg", "is_paid": false, "mblog_vip_type": 0, "user": {"id": 2405056755, "screen_name": "\u5584\u5fc3\u83b2\u5fc3\u5fae\u535a", "profile_image_url": "https://tva1.sinaimg.cn/crop.0.0.180.180.180/8f5a40f3jw1e8qgp5bmzyj2050050aa8.jpg?KID=imgbed,tva&Expires=1642954571&ssig=Mpg%2BSw%2FcW7", "profile_url": "https://m.weibo.cn/u/2405056755?uid=2405056755&luicode=10000011&lfid=1076032405056755", "statuses_count": 2539, "verified": false, "verified_type": -1, "close_blue_v": false, "description": "\u5584\u5fc3\u84ee\u5fc3\uff0c\u842c\u773e\u540c\u5fc3\u3002", "gender": "m", "mbtype": 12, "urank": 37, "mbrank": 7, "follow_me": false, "following": false, "follow_count": 12, "followers_count": "5300", "followers_count_str": "5300", "cover_image_phone": "https://tva1.sinaimg.cn/crop.0.0.640.640.640/549d0121tw1egm1kjly3jj20hs0hsq4f.jpg", "avatar_hd": "https://ww1.sinaimg.cn/orj480/8f5a40f3jw1e8qgp5bmzyj2050050aa8.jpg", "like": false, "like_me": false, "badge": {"bind_taobao": 1, "user_name_certificate": 1, "yiqijuan_2018": 1, "renrengongyijie_2021": 1}}, "picStatus": "0:1,1:1,2:1,3:1,4:1,5:1,6:1,7:1,8:1", "reposts_count": 1, "comments_count": 5, "reprint_cmt_count": 0, "attitudes_count": 15, "pending_approval_count": 0, "isLongText": false, "reward_exhibition_type": 0, "hide_flag": 0, "mlevel": 0, "darwin_tags": [], "mblogtype": 0, "rid": "0_0_50_6559839547052159093_0_0_0", "more_info_type": 0, "extern_safe": 0, "number_display_strategy": {"apply_scenario_flag": 3, "display_text_min_number": 1000000, "display_text": "100\u4e07+"}, "enable_comment_guide": true, "content_auth": 0, "pic_num": 9, "alchemy_params": {"ug_red_envelope": false}, "reprint_type": 0, "can_reprint": false, "new_comment_style": 0, "mblog_menu_new_style": 0, "edit_config": {"edited": false}, "pics": [{"pid": "8f5a40f3ly1g29hszodkej216o16o7wh", "url": "https://wx3.sinaimg.cn/orj360/8f5a40f3ly1g29hszodkej216o16o7wh.jpg", "size": "orj360", "geo": {"width": 360, "height": 360, "croped": false}, "large": {"size": "large", "url": "https://wx3.sinaimg.cn/large/8f5a40f3ly1g29hszodkej216o16o7wh.jpg", "geo": {"width": "1536", "height": "1536", "croped": false}}}, {"pid": "8f5a40f3ly1g29ht0ti64j216o16o4ox", "url": "https://wx2.sinaimg.cn/orj360/8f5a40f3ly1g29ht0ti64j216o16o4ox.jpg", "size": "orj360", "geo": {"width": 360, "height": 360, "croped": false}, "large": {"size": "large", "url": "https://wx2.sinaimg.cn/large/8f5a40f3ly1g29ht0ti64j216o16o4ox.jpg", "geo": {"width": "1536", "height": "1536", "croped": false}}}, {"pid": "8f5a40f3ly1g29ht2sf9hj216o16otyn", "url": "https://wx1.sinaimg.cn/orj360/8f5a40f3ly1g29ht2sf9hj216o16otyn.jpg", "size": "orj360", "geo": {"width": 360, "height": 360, "croped": false}, "large": {"size": "large", "url": "https://wx1.sinaimg.cn/large/8f5a40f3ly1g29ht2sf9hj216o16otyn.jpg", "geo": {"width": "1536", "height": "1536", "croped": false}}}, {"pid": "8f5a40f3ly1g29ht5r84fj216o16o4qp", "url": "https://wx4.sinaimg.cn/orj360/8f5a40f3ly1g29ht5r84fj216o16o4qp.jpg", "size": "orj360", "geo": {"width": 360, "height": 360, "croped": false}, "large": {"size": "large", "url": "https://wx4.sinaimg.cn/large/8f5a40f3ly1g29ht5r84fj216o16o4qp.jpg", "geo": {"width": "1536", "height": "1536", "croped": false}}}, {"pid": "8f5a40f3ly1g29ht7fyecj216o16oe6x", "url": "https://wx1.sinaimg.cn/orj360/8f5a40f3ly1g29ht7fyecj216o16oe6x.jpg", "size": "orj360", "geo": {"width": 360, "height": 360, "croped": false}, "large": {"size": "large", "url": "https://wx1.sinaimg.cn/large/8f5a40f3ly1g29ht7fyecj216o16oe6x.jpg", "geo": {"width": "1536", "height": "1536", "croped": false}}}, {"pid": "8f5a40f3ly1g29ht8nqt4j216o16o7uk", "url": "https://wx2.sinaimg.cn/orj360/8f5a40f3ly1g29ht8nqt4j216o16o7uk.jpg", "size": "orj360", "geo": {"width": 360, "height": 360, "croped": false}, "large": {"size": "large", "url": "https://wx2.sinaimg.cn/large/8f5a40f3ly1g29ht8nqt4j216o16o7uk.jpg", "geo": {"width": "1536", "height": "1536", "croped": false}}}, {"pid": "8f5a40f3ly1g29htb6tjsj216o16o4qp", "url": "https://wx2.sinaimg.cn/orj360/8f5a40f3ly1g29htb6tjsj216o16o4qp.jpg", "size": "orj360", "geo": {"width": 360, "height": 360, "croped": false}, "large": {"size": "large", "url": "https://wx2.sinaimg.cn/large/8f5a40f3ly1g29htb6tjsj216o16o4qp.jpg", "geo": {"width": "1536", "height": "1536", "croped": false}}}, {"pid": "8f5a40f3ly1g29htdrxhjj216o16o1kx", "url": "https://wx3.sinaimg.cn/orj360/8f5a40f3ly1g29htdrxhjj216o16o1kx.jpg", "size": "orj360", "geo": {"width": 360, "height": 360, "croped": false}, "large": {"size": "large", "url": "https://wx3.sinaimg.cn/large/8f5a40f3ly1g29htdrxhjj216o16o1kx.jpg", "geo": {"width": "1536", "height": "1536", "croped": false}}}, {"pid": "8f5a40f3ly1g29htghwxcj216o16okib", "url": "https://wx3.sinaimg.cn/orj360/8f5a40f3ly1g29htghwxcj216o16okib.jpg", "size": "orj360", "geo": {"width": 360, "height": 360, "croped": false}, "large": {"size": "large", "url": "https://wx3.sinaimg.cn/large/8f5a40f3ly1g29htghwxcj216o16okib.jpg", "geo": {"width": "1536", "height": "1536", "croped": false}}}], "bid": "Hqyps7Kx8"}